django_easy_report/__init__.py
django_easy_report/actions.py
django_easy_report/admin.py
django_easy_report/apps.py
django_easy_report/choices.py
django_easy_report/constants.py
django_easy_report/exceptions.py
django_easy_report/forms.py
django_easy_report/models.py
django_easy_report/reports.py
django_easy_report/serializers.py
django_easy_report/tasks.py
django_easy_report/urls.py
django_easy_report/utils.py
django_easy_report/views.py
django_easy_report/management/__init__.py
django_easy_report/management/commands/__init__.py
django_easy_report/management/commands/clean_reports.py
django_easy_report/migrations/0001_initial.py
django_easy_report/migrations/0002_secretkey_secretreplace.py
django_easy_report/migrations/__init__.py
django_easy_report/tests/__init__.py
django_easy_report/tests/test_admin.py
django_easy_report/tests/test_downloader.py
django_easy_report/tests/test_example.py
django_easy_report/tests/test_models_functions.py
django_easy_report/tests/test_models_validation.py
django_easy_report/tests/test_report_flow.py
django_easy_report/tests/test_report_generation.py
django_easy_report/tests/test_secret.py
django_easy_report-0.2.0.dist-info/LICENSE
django_easy_report-0.2.0.dist-info/METADATA
django_easy_report-0.2.0.dist-info/WHEEL
django_easy_report-0.2.0.dist-info/top_level.txt
django_easy_report-0.2.0.dist-info/RECORD
