Metadata-Version: 2.1
Name: django-easy-report
Version: 0.2.0
Summary: Django app for report generation
Home-page: https://github.com/ehooo/django_easy_report
Author: Victor Torre
Author-email: web.ehooo@gmail.com
License: UNKNOWN
Project-URL: Bug Tracker, https://github.com/ehooo/django_easy_report/issues
Platform: UNKNOWN
Classifier: Programming Language :: Python :: 3
Classifier: License :: OSI Approved :: MIT License
Classifier: Operating System :: OS Independent
Requires-Python: >=3.5
Requires-Dist: celery
Requires-Dist: django
